logmonitor/__init__.py
time_series_moving_stats/__init__.py
logmonitor-0.0.7a1.dist-info/LICENSE.txt
logmonitor-0.0.7a1.dist-info/METADATA
logmonitor-0.0.7a1.dist-info/WHEEL
logmonitor-0.0.7a1.dist-info/entry_points.txt
logmonitor-0.0.7a1.dist-info/top_level.txt
logmonitor-0.0.7a1.dist-info/RECORD
