Metadata-Version: 2.1
Name: logmonitor
Version: 0.0.7a1
Summary: A simple log monitor application that parses an actively written log and outputs useful statistics.
Home-page: https://github.com/FConstantinos/logmonitor
Author: Konstantinos Fragkiadakis
Author-email: fconstantinos@gmail.com
License: UNKNOWN
Project-URL: Bug Reports, https://github.com/FConstantinos/logmonitor/issues
Project-URL: Source, https://github.com/FConstantinos/logmonitor/
Keywords: logging,monitoring,development
Platform: any
Classifier: Development Status :: 3 - Alpha
Classifier: Intended Audience :: Developers
Classifier: Topic :: System :: Monitoring
Classifier: License :: OSI Approved :: MIT License
Classifier: Programming Language :: Python :: 3.6
Classifier: Programming Language :: Python :: 3.7
Classifier: Programming Language :: Python :: 3.8
Classifier: Programming Language :: Python :: 3 :: Only
Requires-Python: >=3.6.9, <4
Requires-Dist: sh
Requires-Dist: apachelogs
Provides-Extra: dev
Requires-Dist: pytest ; extra == 'dev'
Requires-Dist: log-generator ; extra == 'dev'
Requires-Dist: wheel ; extra == 'dev'
Provides-Extra: test
Requires-Dist: pytest ; extra == 'test'
Requires-Dist: log-generator ; extra == 'test'
